{
  "outbounds": [
    {
      "type": "wireguard",
      "tag": "proxy",
      "local_address": "10.0.0.2/32",
      "private_key": "cCnNaOrHjS5EpblCVVEQThkdZbOA8yM3OuFvmGugVkw=",
      "server": "dawsh.shomarekartbef.rest",
      "server_port": 41131,
      "peer_public_key": "Fp+g+81E7r4WhORbV7W29WG6/qwq1sPHjjJFyueT2jw=",
      "pre_shared_key": "oyt8yHBi3ULXuUFrCbvKTwYnzs1Zi4GX83rY8f2Nq+c=",
      "mtu": 1180,
      "fake_packets": "10-20",
      "fake_packets_size": "20-40",
      "fake_packets_delay": "30-50"
    }
  ]
}
